yamep/__init__.py
yamep/main.py
yamep/markdown_editor_app.py
yamep/resources/markdown_syntax_examples.md
yamep/resources/yamep.png
yamep/themes/blue_theme.qss
yamep/themes/dark_theme.qss
yamep/themes/light_theme.qss
yamep/themes/markdown_style.css
yamep/themes/markdown_style_blue.css
yamep/themes/markdown_style_dark.css
yamep/themes/markdown_style_light.css
yamep-1.0.1.dist-info/LICENSE
yamep-1.0.1.dist-info/METADATA
yamep-1.0.1.dist-info/WHEEL
yamep-1.0.1.dist-info/entry_points.txt
yamep-1.0.1.dist-info/top_level.txt
yamep-1.0.1.dist-info/RECORD
