Metadata-Version: 2.1
Name: yamep
Version: 1.0.1
Summary: YAMEP - Yet Another Markdown Editor in Python
Home-page: https://codeberg.org/tomsh/yamep
Author: tomsh
Author-email: tomsh@disroot.org
License: MIT
Classifier: Programming Language :: Python :: 3
Classifier: License :: OSI Approved :: MIT License
License-File: LICENSE
Requires-Dist: PySide6
Requires-Dist: markdown
Requires-Dist: pymdown-extensions
Requires-Dist: platformdirs
